{"data": {"items": [{"id": 499202, "index_code": "SZ399393", "name": "国证地产", "ttype": "3", "pe": 0, "pb": 0.8409, "pe_percentile": 0, "pb_percentile": 0.168, "roe": 0, "yeild": 0.0111, "ts": 1767110400000, "eva_type": "low", "eva_type_int": 0, "url": "https://danjuanfunds.com/funding/160218?channel=1800100001&source=guzhi__web_20171001", "bond_yeild": 0.05, "begin_at": 1442851200000, "created_at": 1767177123644, "updated_at": 1767177123644, "pb_flag": true, "source": "5", "date": "12-31", "pb_over_history": 0.832, "pe_over_history": 1}, {"id": 499176, "index_code": "SZ399812", "name": "养老产业", "ttype": "3", "pe": 12.8293, "pb": 2.114, "pe_percentile": 0.014, "pb_percentile": 0.2024, "roe": 0.1648, "yeild": 0.0214, "ts": 1767110400000, "eva_type": "low", "eva_type_int": 0, "url": "https://danjuanfunds.com/funding/000968?channel=1800100001&source=guzhi__web_20171001", "bond_yeild": 0.05, "begin_at": 1442851200000, "created_at": 1767177121514, "updated_at": 1767177121514, "peg": 0.8064, "pb_flag": false, "source": "5", "date": "12-31", "pb_over_history": 0.7976, "pe_over_history": 0.986}, {"id": 499171, "index_code": "SZ399997", "name": "中证白酒", "ttype": "3", "pe": 18.2382, "pb": 4.8213, "pe_percentile": 0.0304, "pb_percentile": 0.1464, "roe": 0.2644, "yeild": 0.0447, "ts": 1767110400000, "eva_type": "low", "eva_type_int": 0, "url": "https://danjuanfunds.com/funding/161725?channel=1800100001&source=guzhi__web_20171001", "bond_yeild": 0.05, "begin_at": 1442851200000, "created_at": 1767177121113, "updated_at": 1767177121113, "peg": 32.3856, "pb_flag": false, "source": "5", "date": "12-31", "pb_over_history": 0.8536, "pe_over_history": 0.9696}, {"id": 499210, "index_code": "CSIH30094", "name": "消费红利", "ttype": "2", "pe": 18.3015, "pb": 4.1595, "pe_percentile": 0.0108, "pb_percentile": 0.1652, "roe": 0.2273, "yeild": 0.0446, "ts": 1767110400000, "eva_type": "low", "eva_type_int": 0, "url": "", "bond_yeild": 0.05, "begin_at": 1442764800000, "created_at": 1767177124197, "updated_at": 1767177124197, "peg": 7.4257, "pb_flag": false, "source": "5", "date": "12-31", "pb_over_history": 0.8348, "pe_over_history": 0.9892}, {"id": 499187, "index_code": "SH000932", "name": "主要消费", "ttype": "3", "pe": 18.9933, "pb": 4.0151, "pe_percentile": 0.0152, "pb_percentile": 0.146, "roe": 0.2114, "yeild": 0.0388, "ts": 1767110400000, "eva_type": "low", "eva_type_int": 0, "url": "https://danjuanfunds.com/funding/000248?channel=1800100001&source=guzhi__web_20171001", "bond_yeild": 0.05, "begin_at": 1442851200000, "created_at": 1767177122366, "updated_at": 1767177122366, "peg": 3.4099, "pb_flag": false, "source": "5", "date": "12-31", "pb_over_history": 0.854, "pe_over_history": 0.9848}, {"id": 499195, "index_code": "CSIH30533", "name": "中概互联50", "ttype": "3", "pe": 19.28, "pb": 2.8908, "pe_percentile": 0.1244, "pb_percentile": 0.2844, "roe": 0.1499, "yeild": 0.0091, "ts": 1767110400000, "eva_type": "low", "eva_type_int": 0, "url": "https://danjuanfunds.com/funding/006327?channel=1800100001&source=guzhi__web_20171001", "bond_yeild": 0.05, "begin_at": 1442851200000, "created_at": 1767177123046, "updated_at": 1767177123046, "pb_flag": false, "source": "5", "date": "12-31", "pb_over_history": 0.7156, "pe_over_history": 0.8756}, {"id": 499154, "index_code": "CSIH11136", "name": "中国互联", "ttype": "3", "pe": 19.3239, "pb": 2.8779, "pe_percentile": 0.1416, "pb_percentile": 0.2976, "roe": 0.1489, "yeild": 0.0096, "ts": 1767024000000, "eva_type": "low", "eva_type_int": 0, "url": "https://danjuanfunds.com/funding/164906?channel=1800100001&source=guzhi__web_20171001", "bond_yeild": 0.05, "begin_at": 1442764800000, "created_at": 1767144721007, "updated_at": 1767144721007, "pb_flag": false, "source": "5", "date": "12-30", "pb_over_history": 0.7024, "pe_over_history": 0.8584}, {"id": 499175, "index_code": "SZ399396", "name": "国证食品", "ttype": "3", "pe": 20.4216, "pb": 4.1862, "pe_percentile": 0.0308, "pb_percentile": 0.0764, "roe": 0.205, "yeild": 0.0398, "ts": 1767110400000, "eva_type": "low", "eva_type_int": 0, "url": "https://danjuanfunds.com/funding/160222?channel=1800100001&source=guzhi__web_20171001", "bond_yeild": 0.05, "begin_at": 1442851200000, "created_at": 1767177121429, "updated_at": 1767177121429, "peg": 5.2137, "pb_flag": false, "source": "5", "date": "12-31", "pb_over_history": 0.9236, "pe_over_history": 0.9692}, {"id": 499204, "index_code": "SZ399989", "name": "中证医疗", "ttype": "3", "pe": 32.2411, "pb": 3.417, "pe_percentile": 0.286, "pb_percentile": 0.0664, "roe": 0.106, "yeild": 0.0145, "ts": 1767110400000, "eva_type": "low", "eva_type_int": 0, "url": "", "bond_yeild": 0.05, "begin_at": 1442851200000, "created_at": 1767177123802, "updated_at": 1767177123802, "peg": 1.3498, "pb_flag": false, "source": "5", "date": "12-31", "pb_over_history": 0.9336, "pe_over_history": 0.714}, {"id": 499174, "index_code": "SZ399975", "name": "证券公司", "ttype": "3", "pe": 17.3257, "pb": 1.4902, "pe_percentile": 0.1596, "pb_percentile": 0.3908, "roe": 0.086, "yeild": 0.0139, "ts": 1767110400000, "eva_type": "mid", "eva_type_int": 1, "url": "https://danjuanfunds.com/funding/006098?channel=1800100001&source=guzhi__web_20171001", "bond_yeild": 0.05, "begin_at": 1442851200000, "created_at": 1767177121359, "updated_at": 1767177121359, "peg": 0.6895, "pb_flag": true, "source": "5", "date": "12-31", "pb_over_history": 0.6092, "pe_over_history": 0.8404}, {"id": 499211, "index_code": "HKHSTECH", "name": "恒生科技", "ttype": "3", "pe": 22.8722, "pb": 3.0315, "pe_percentile": 0.2937, "pb_percentile": 0.5958, "roe": 0.1325, "yeild": 0.01, "ts": 1767110400000, "eva_type": "mid", "eva_type_int": 1, "url": "", "bond_yeild": 0.05, "begin_at": 1595779200000, "created_at": 1767177124270, "updated_at": 1767177124270, "pb_flag": false, "source": "5", "date": "12-31", "pb_over_history": 0.4042, "pe_over_history": 0.7063}, {"id": 499178, "index_code": "SH000991", "name": "全指医药", "ttype": "3", "pe": 33.2676, "pb": 3.1399, "pe_percentile": 0.3824, "pb_percentile": 0.1172, "roe": 0.0944, "yeild": 0.0158, "ts": 1767110400000, "eva_type": "mid", "eva_type_int": 1, "url": "https://danjuanfunds.com/funding/001180?channel=1800100001&source=guzhi__web_20171001", "bond_yeild": 0.05, "begin_at": 1442851200000, "created_at": 1767177121653, "updated_at": 1767177121653, "peg": 1.5356, "pb_flag": false, "source": "5", "date": "12-31", "pb_over_history": 0.8828, "pe_over_history": 0.6176}, {"id": 499193, "index_code": "SH000978", "name": "医药100", "ttype": "3", "pe": 33.3876, "pb": 3.1974, "pe_percentile": 0.4196, "pb_percentile": 0.1248, "roe": 0.0958, "yeild": 0.0154, "ts": 1767110400000, "eva_type": "mid", "eva_type_int": 1, "url": "https://danjuanfunds.com/funding/001550?channel=1800100001&source=guzhi__web_20171001", "bond_yeild": 0.05, "begin_at": 1442851200000, "created_at": 1767177122871, "updated_at": 1767177122871, "peg": 1.5985, "pb_flag": false, "source": "5", "date": "12-31", "pb_over_history": 0.8752, "pe_over_history": 0.5804}, {"id": 499159, "index_code": "SPACEVCP", "name": "标普价值", "ttype": "2", "pe": 7.2433, "pb": 0.7984, "pe_percentile": 0.6916, "pb_percentile": 0.6664, "roe": 0.1102, "yeild": 0.0428, "ts": 1767110400000, "eva_type": "high", "eva_type_int": 2, "url": "https://danjuanfunds.com/funding/501310?channel=1800100001&source=guzhi__web_20171001", "bond_yeild": 0.05, "begin_at": 1442937600000, "created_at": 1767177120071, "updated_at": 1767177120071, "peg": 1.6806, "pb_flag": false, "source": "5", "date": "12-31", "pb_over_history": 0.3336, "pe_over_history": 0.3084}, {"id": 499169, "index_code": "SZ399986", "name": "中证银行", "ttype": "3", "pe": 7.2446, "pb": 0.7067, "pe_percentile": 0.9148, "pb_percentile": 0.4164, "roe": 0.0975, "yeild": 0.0499, "ts": 1767110400000, "eva_type": "high", "eva_type_int": 2, "url": "https://danjuanfunds.com/funding/240019?channel=1800100001&source=guzhi__web_20171001", "bond_yeild": 0.05, "begin_at": 1442851200000, "created_at": 1767177120937, "updated_at": 1767177120937, "peg": 3.8375, "pb_flag": true, "source": "5", "date": "12-31", "pb_over_history": 0.5836, "pe_over_history": 0.0852}, {"id": 499197, "index_code": "CSI931157", "name": "红利成长LV", "ttype": "2", "pe": 8.016, "pb": 0.8682, "pe_percentile": 0.6517, "pb_percentile": 0.5668, "roe": 0.1083, "yeild": 0.0522, "ts": 1767110400000, "eva_type": "high", "eva_type_int": 2, "url": "https://danjuanfunds.com/funding/007751?channel=1800100001&source=guzhi__web_20171001", "bond_yeild": 0.05, "begin_at": 1556121600000, "created_at": 1767177123246, "updated_at": 1767177123246, "peg": 1.0265, "pb_flag": false, "source": "5", "date": "12-31", "pb_over_history": 0.4332, "pe_over_history": 0.3483}, {"id": 499185, "index_code": "CSIH30269", "name": "红利低波", "ttype": "2", "pe": 8.5003, "pb": 0.8914, "pe_percentile": 0.79, "pb_percentile": 0.5788, "roe": 0.1049, "yeild": 0.0498, "ts": 1767110400000, "eva_type": "high", "eva_type_int": 2, "url": "https://danjuanfunds.com/funding/005279?channel=1800100001&source=guzhi__web_20171001", "bond_yeild": 0.05, "begin_at": 1442851200000, "created_at": 1767177122205, "updated_at": 1767177122205, "peg": 3.6598, "pb_flag": false, "source": "5", "date": "12-31", "pb_over_history": 0.4212, "pe_over_history": 0.21}, {"id": 499168, "index_code": "SH000922", "name": "中证红利", "ttype": "2", "pe": 8.5511, "pb": 0.8662, "pe_percentile": 0.7828, "pb_percentile": 0.4836, "roe": 0.1013, "yeild": 0.0507, "ts": 1767110400000, "eva_type": "high", "eva_type_int": 2, "url": "https://danjuanfunds.com/funding/090010?channel=1800100001&source=guzhi__web_20171001", "bond_yeild": 0.05, "begin_at": 1442851200000, "created_at": 1767177120864, "updated_at": 1767177120864, "peg": 6.5547, "pb_flag": false, "source": "5", "date": "12-31", "pb_over_history": 0.5164, "pe_over_history": 0.2172}, {"id": 499207, "index_code": "SH000015", "name": "上证红利", "ttype": "2", "pe": 8.5932, "pb": 0.8545, "pe_percentile": 0.9328, "pb_percentile": 0.5752, "roe": 0.0994, "yeild": 0.0528, "ts": 1767110400000, "eva_type": "high", "eva_type_int": 2, "url": "", "bond_yeild": 0.05, "begin_at": 1442505600000, "created_at": 1767177124012, "updated_at": 1767177124012, "peg": 32.275, "pb_flag": false, "source": "5", "date": "12-31", "pb_over_history": 0.4248, "pe_over_history": 0.0672}, {"id": 499199, "index_code": "CSPSADRP", "name": "标普红利", "ttype": "2", "pe": 8.8527, "pb": 0.9628, "pe_percentile": 0.928, "pb_percentile": 0.6224, "roe": 0.1088, "yeild": 0.0516, "ts": 1767110400000, "eva_type": "high", "eva_type_int": 2, "url": "https://danjuanfunds.com/funding/501029?channel=1800100001&source=guzhi__web_20171001", "bond_yeild": 0.05, "begin_at": 1442764800000, "created_at": 1767177123425, "updated_at": 1767177123425, "peg": 5.9412, "pb_flag": false, "source": "5", "date": "12-31", "pb_over_history": 0.3776, "pe_over_history": 0.072}, {"id": 499203, "index_code": "CSI930740", "name": "300红利LV", "ttype": "2", "pe": 9.1732, "pb": 0.9568, "pe_percentile": 0.8532, "pb_percentile": 0.602, "roe": 0.1043, "yeild": 0.0478, "ts": 1767110400000, "eva_type": "high", "eva_type_int": 2, "url": "https://danjuanfunds.com/funding/007605?channel=1800100001&source=guzhi__web_20171001", "bond_yeild": 0.05, "begin_at": 1441900800000, "created_at": 1767177123730, "updated_at": 1767177123730, "peg": 4.344, "pb_flag": false, "source": "5", "date": "12-31", "pb_over_history": 0.398, "pe_over_history": 0.1468}, {"id": 499188, "index_code": "SH000919", "name": "300价值", "ttype": "2", "pe": 9.1819, "pb": 0.9573, "pe_percentile": 0.7668, "pb_percentile": 0.522, "roe": 0.1043, "yeild": 0.0429, "ts": 1767110400000, "eva_type": "high", "eva_type_int": 2, "url": "https://danjuanfunds.com/funding/310398?channel=1800100001&source=guzhi__web_20171001", "bond_yeild": 0.05, "begin_at": 1442851200000, "created_at": 1767177122453, "updated_at": 1767177122453, "peg": 2.1903, "pb_flag": false, "source": "5", "date": "12-31", "pb_over_history": 0.478, "pe_over_history": 0.2332}, {"id": 499164, "index_code": "SH000170", "name": "50AH优选", "ttype": "1", "pe": 10.0294, "pb": 1.1576, "pe_percentile": 0.6589, "pb_percentile": 0.6573, "roe": 0.1154, "yeild": 0.0315, "ts": 1767110400000, "eva_type": "high", "eva_type_int": 2, "url": "https://danjuanfunds.com/funding/501050?channel=1800100001&source=guzhi__web_20171001", "bond_yeild": 0.05, "begin_at": 1449676800000, "created_at": 1767177120528, "updated_at": 1767177120528, "peg": 1.5267, "pb_flag": false, "source": "5", "date": "12-31", "pb_over_history": 0.3427, "pe_over_history": 0.3411}, {"id": 499181, "index_code": "SZ399550", "name": "央视50", "ttype": "2", "pe": 10.0876, "pb": 1.0521, "pe_percentile": 0.7932, "pb_percentile": 0.292, "roe": 0.1043, "yeild": 0.0442, "ts": 1767110400000, "eva_type": "high", "eva_type_int": 2, "url": "https://danjuanfunds.com/funding/165312?channel=1800100001&source=guzhi__web_20171001", "bond_yeild": 0.05, "begin_at": 1442764800000, "created_at": 1767177121907, "updated_at": 1767177121907, "peg": 1.8676, "pb_flag": false, "source": "5", "date": "12-31", "pb_over_history": 0.708, "pe_over_history": 0.2068}, {"id": 499153, "index_code": "HSFML25", "name": "香港大盘", "ttype": "1", "pe": 10.112, "pb": 1.0322, "pe_percentile": 0.7612, "pb_percentile": 0.5524, "roe": 0.1021, "yeild": 0.0325, "ts": 1767024000000, "eva_type": "high", "eva_type_int": 2, "url": "https://danjuanfunds.com/funding/501301?channel=1800100001&source=guzhi__web_20171001", "bond_yeild": 0.05, "begin_at": 1442764800000, "created_at": 1767144720654, "updated_at": 1767144720654, "peg": 1.1508, "pb_flag": false, "source": "5", "date": "12-30", "pb_over_history": 0.4476, "pe_over_history": 0.2388}, {"id": 499180, "index_code": "SH000925", "name": "基本面50", "ttype": "2", "pe": 10.1903, "pb": 1.0556, "pe_percentile": 0.8316, "pb_percentile": 0.4536, "roe": 0.1036, "yeild": 0.0413, "ts": 1767110400000, "eva_type": "high", "eva_type_int": 2, "url": "https://danjuanfunds.com/funding/160716?channel=1800100001&source=guzhi__web_20171001", "bond_yeild": 0.05, "begin_at": 1442851200000, "created_at": 1767177121836, "updated_at": 1767177121836, "peg": 1.9196, "pb_flag": false, "source": "5", "date": "12-31", "pb_over_history": 0.5464, "pe_over_history": 0.1684}, {"id": 499152, "index_code": "HKHSCEI", "name": "国企指数", "ttype": "1", "pe": 10.5212, "pb": 1.0746, "pe_percentile": 0.876, "pb_percentile": 0.7832, "roe": 0.1021, "yeild": 0.0308, "ts": 1767024000000, "eva_type": "high", "eva_type_int": 2, "url": "https://danjuanfunds.com/funding/160717?channel=1800100001&source=guzhi__web_20171001", "bond_yeild": 0.05, "begin_at": 1442764800000, "created_at": 1767144720555, "updated_at": 1767144720555, "peg": 1.8275, "pb_flag": false, "source": "5", "date": "12-30", "pb_over_history": 0.2168, "pe_over_history": 0.124}, {"id": 499161, "index_code": "SH000016", "name": "上证50", "ttype": "1", "pe": 11.8473, "pb": 1.2998, "pe_percentile": 0.8868, "pb_percentile": 0.7348, "roe": 0.1097, "yeild": 0.0359, "ts": 1767110400000, "eva_type": "high", "eva_type_int": 2, "url": "https://danjuanfunds.com/funding/110003?channel=1800100001&source=guzhi__web_20171001", "bond_yeild": 0.05, "begin_at": 1442851200000, "created_at": 1767177120255, "updated_at": 1767177120255, "peg": 1.9913, "pb_flag": false, "source": "5", "date": "12-31", "pb_over_history": 0.2652, "pe_over_history": 0.1132}, {"id": 499151, "index_code": "HKHSI", "name": "恒生指数", "ttype": "1", "pe": 11.8564, "pb": 1.2046, "pe_percentile": 0.774, "pb_percentile": 0.7936, "roe": 0.1016, "yeild": 0.033, "ts": 1767024000000, "eva_type": "high", "eva_type_int": 2, "url": "https://danjuanfunds.com/funding/000071?channel=1800100001&source=guzhi__web_20171001", "bond_yeild": 0.05, "begin_at": 1442764800000, "created_at": 1767144720465, "updated_at": 1767144720465, "peg": 1.6293, "pb_flag": false, "source": "5", "date": "12-30", "pb_over_history": 0.2064, "pe_over_history": 0.226}, {"id": 499191, "index_code": "SH000010", "name": "上证180", "ttype": "1", "pe": 12.2156, "pb": 1.2759, "pe_percentile": 0.8416, "pb_percentile": 0.5244, "roe": 0.1044, "yeild": 0.0316, "ts": 1767110400000, "eva_type": "high", "eva_type_int": 2, "url": "https://danjuanfunds.com/funding/040180?channel=1800100001&source=guzhi__web_20171001", "bond_yeild": 0.05, "begin_at": 1442851200000, "created_at": 1767177122694, "updated_at": 1767177122694, "peg": 1.8098, "pb_flag": false, "source": "5", "date": "12-31", "pb_over_history": 0.4756, "pe_over_history": 0.1584}, {"id": 499162, "index_code": "SH000300", "name": "沪深300", "ttype": "1", "pe": 14.1724, "pb": 1.4911, "pe_percentile": 0.8544, "pb_percentile": 0.6136, "roe": 0.1052, "yeild": 0.0278, "ts": 1767110400000, "eva_type": "high", "eva_type_int": 2, "url": "https://danjuanfunds.com/funding/100038?channel=1800100001&source=guzhi__web_20171001", "bond_yeild": 0.05, "begin_at": 1442851200000, "created_at": 1767177120359, "updated_at": 1767177120359, "peg": 1.5093, "pb_flag": false, "source": "5", "date": "12-31", "pb_over_history": 0.3864, "pe_over_history": 0.1456}, {"id": 499205, "index_code": "CSI716567", "name": "MSCI中国", "ttype": "1", "pe": 14.7173, "pb": 1.5231, "pe_percentile": 0.8395, "pb_percentile": 0.665, "roe": 0.1035, "yeild": 0.0265, "ts": 1767110400000, "eva_type": "high", "eva_type_int": 2, "url": "", "bond_yeild": 0.05, "begin_at": 1508688000000, "created_at": 1767177123876, "updated_at": 1767177123876, "peg": 1.3194, "pb_flag": false, "source": "5", "date": "12-31", "pb_over_history": 0.335, "pe_over_history": 0.1605}, {"id": 499183, "index_code": "SZ399324", "name": "深证红利", "ttype": "2", "pe": 15.5266, "pb": 2.4539, "pe_percentile": 0.4756, "pb_percentile": 0.7968, "roe": 0.158, "yeild": 0.0432, "ts": 1767110400000, "eva_type": "high", "eva_type_int": 2, "url": "https://danjuanfunds.com/funding/481012?channel=1800100001&source=guzhi__web_20171001", "bond_yeild": 0.05, "begin_at": 1442851200000, "created_at": 1767177122065, "updated_at": 1767177122065, "peg": 1.8186, "pb_flag": false, "source": "5", "date": "12-31", "pb_over_history": 0.2032, "pe_over_history": 0.5244}, {"id": 499160, "index_code": "SPCQVCP", "name": "标普质量", "ttype": "2", "pe": 15.6419, "pb": 2.777, "pe_percentile": 0.4188, "pb_percentile": 0.3848, "roe": 0.1775, "yeild": 0.0208, "ts": 1767110400000, "eva_type": "high", "eva_type_int": 2, "url": "https://danjuanfunds.com/funding/501069?channel=1800100001&source=guzhi__web_20171001", "bond_yeild": 0.05, "begin_at": 1442851200000, "created_at": 1767177120170, "updated_at": 1767177120170, "peg": 1.8252, "pb_flag": false, "source": "5", "date": "12-31", "pb_over_history": 0.6152, "pe_over_history": 0.5812}, {"id": 499172, "index_code": "SZ399998", "name": "中证煤炭", "ttype": "3", "pe": 16.1141, "pb": 1.5553, "pe_percentile": 0.7888, "pb_percentile": 0.7976, "roe": 0.0965, "yeild": 0.0604, "ts": 1767110400000, "eva_type": "high", "eva_type_int": 2, "url": "https://danjuanfunds.com/funding/161724?channel=1800100001&source=guzhi__web_20171001", "bond_yeild": 0.05, "begin_at": 1439308800000, "created_at": 1767177121204, "updated_at": 1767177121204, "pb_flag": true, "source": "5", "date": "12-31", "pb_over_history": 0.2024, "pe_over_history": 0.2112}, {"id": 499182, "index_code": "SH000903", "name": "中证100", "ttype": "1", "pe": 17.395, "pb": 1.8726, "pe_percentile": 0.9988, "pb_percentile": 0.986, "roe": 0.1077, "yeild": 0.0272, "ts": 1767110400000, "eva_type": "high", "eva_type_int": 2, "url": "https://danjuanfunds.com/funding/240014?channel=1800100001&source=guzhi__web_20171001", "bond_yeild": 0.05, "begin_at": 1442851200000, "created_at": 1767177121993, "updated_at": 1767177121993, "peg": 1.5631, "pb_flag": false, "source": "5", "date": "12-31", "pb_over_history": 0.014, "pe_over_history": 0.0012}, {"id": 499196, "index_code": "CSI931142", "name": "东证竞争", "ttype": "2", "pe": 17.8782, "pb": 3.1122, "pe_percentile": 0.9468, "pb_percentile": 0.948, "roe": 0.1741, "yeild": 0.0223, "ts": 1767110400000, "eva_type": "high", "eva_type_int": 2, "url": "https://danjuanfunds.com/funding/007658?channel=1800100001&source=guzhi__web_20171001", "bond_yeild": 0.05, "begin_at": 1442851200000, "created_at": 1767177123172, "updated_at": 1767177123172, "peg": 1.0045, "pb_flag": false, "source": "5", "date": "12-31", "pb_over_history": 0.052, "pe_over_history": 0.0532}, {"id": 499155, "index_code": "SPHCMSHP", "name": "香港中小", "ttype": "1", "pe": 18.4481, "pb": 1.4414, "pe_percentile": 0.9562, "pb_percentile": 0.7076, "roe": 0.0781, "yeild": 0.0256, "ts": 1767024000000, "eva_type": "high", "eva_type_int": 2, "url": "https://danjuanfunds.com/funding/501021?channel=1800100001&source=guzhi__web_20171001", "bond_yeild": 0.05, "begin_at": 1467907200000, "created_at": 1767144721154, "updated_at": 1767144721154, "pb_flag": false, "source": "5", "date": "12-30", "pb_over_history": 0.2924, "pe_over_history": 0.0438}, {"id": 499213, "index_code": "GDAXI", "name": "德国DAX", "ttype": "1", "pe": 19.2808, "pb": 2.074, "pe_percentile": 0.6684, "pb_percentile": 0.9952, "roe": 0.1076, "yeild": 0.0237, "ts": 1767110400000, "eva_type": "high", "eva_type_int": 2, "url": "https://danjuanfunds.com/funding/000614?channel=1800100001&source=guzhi__web_20171001", "bond_yeild": 0.05, "begin_at": 1442764800000, "created_at": 1767177124397, "updated_at": 1767177124397, "pb_flag": false, "source": "5", "date": "12-31", "pb_over_history": 0.0048, "pe_over_history": 0.3316}, {"id": 499184, "index_code": "CSI930782", "name": "500低波", "ttype": "2", "pe": 20.4221, "pb": 1.6913, "pe_percentile": 0.543, "pb_percentile": 0.7422, "roe": 0.0828, "yeild": 0.0228, "ts": 1767110400000, "eva_type": "high", "eva_type_int": 2, "url": "https://danjuanfunds.com/funding/003318?channel=1800100001&source=guzhi__web_20171001", "bond_yeild": 0.05, "begin_at": 1454515200000, "created_at": 1767177122135, "updated_at": 1767177122135, "peg": 1.1609, "pb_flag": false, "source": "5", "date": "12-31", "pb_over_history": 0.2578, "pe_over_history": 0.457}, {"id": 499189, "index_code": "SZ399701", "name": "基本面60", "ttype": "2", "pe": 21.3853, "pb": 2.0608, "pe_percentile": 0.7208, "pb_percentile": 0.3084, "roe": 0.0964, "yeild": 0.0269, "ts": 1767110400000, "eva_type": "high", "eva_type_int": 2, "url": "https://danjuanfunds.com/funding/530015?channel=1800100001&source=guzhi__web_20171001", "bond_yeild": 0.05, "begin_at": 1442851200000, "created_at": 1767177122525, "updated_at": 1767177122525, "peg": 0.9481, "pb_flag": false, "source": "5", "date": "12-31", "pb_over_history": 0.6916, "pe_over_history": 0.2792}, {"id": 499186, "index_code": "SZ399317", "name": "国证A指", "ttype": "1", "pe": 21.6333, "pb": 1.8146, "pe_percentile": 0.9456, "pb_percentile": 0.5736, "roe": 0.0839, "yeild": 0.0195, "ts": 1767110400000, "eva_type": "high", "eva_type_int": 2, "url": "https://danjuanfunds.com/funding/005414?channel=1800100001&source=guzhi__web_20171001", "bond_yeild": 0.05, "begin_at": 1442851200000, "created_at": 1767177122278, "updated_at": 1767177122278, "peg": 1.4115, "pb_flag": false, "source": "5", "date": "12-31", "pb_over_history": 0.4264, "pe_over_history": 0.0544}, {"id": 499190, "index_code": "SZ399702", "name": "基本面120", "ttype": "2", "pe": 22.4899, "pb": 2.1554, "pe_percentile": 0.8508, "pb_percentile": 0.43, "roe": 0.0958, "yeild": 0.0243, "ts": 1767110400000, "eva_type": "high", "eva_type_int": 2, "url": "https://danjuanfunds.com/funding/070023?channel=1800100001&source=guzhi__web_20171001", "bond_yeild": 0.05, "begin_at": 1442851200000, "created_at": 1767177122595, "updated_at": 1767177122595, "peg": 0.9262, "pb_flag": false, "source": "5", "date": "12-31", "pb_over_history": 0.57, "pe_over_history": 0.1492}, {"id": 499177, "index_code": "SH000989", "name": "全指可选", "ttype": "3", "pe": 23.0052, "pb": 2.5276, "pe_percentile": 0.3312, "pb_percentile": 0.458, "roe": 0.1099, "yeild": 0.0229, "ts": 1767110400000, "eva_type": "high", "eva_type_int": 2, "url": "https://danjuanfunds.com/funding/001133?channel=1800100001&source=guzhi__web_20171001", "bond_yeild": 0.05, "begin_at": 1442851200000, "created_at": 1767177121584, "updated_at": 1767177121584, "peg": 1.2411, "pb_flag": false, "source": "5", "date": "12-31", "pb_over_history": 0.542, "pe_over_history": 0.6688}, {"id": 499158, "index_code": "HKHSSCNE", "name": "新经济", "ttype": "2", "pe": 24.5723, "pb": 3.3829, "pe_percentile": 0.5316, "pb_percentile": 0.7562, "roe": 0.1377, "yeild": 0.0097, "ts": 1767024000000, "eva_type": "high", "eva_type_int": 2, "url": "", "bond_yeild": 0.05, "begin_at": 1542729600000, "created_at": 1767144721706, "updated_at": 1767144721706, "pb_flag": false, "source": "5", "date": "12-30", "pb_over_history": 0.2438, "pe_over_history": 0.4684}, {"id": 499165, "index_code": "SZ399330", "name": "深证100", "ttype": "1", "pe": 25.4121, "pb": 2.944, "pe_percentile": 0.7884, "pb_percentile": 0.5724, "roe": 0.1159, "yeild": 0.0195, "ts": 1767110400000, "eva_type": "high", "eva_type_int": 2, "url": "https://danjuanfunds.com/funding/217016?channel=1800100001&source=guzhi__web_20171001", "bond_yeild": 0.05, "begin_at": 1442851200000, "created_at": 1767177120616, "updated_at": 1767177120616, "peg": 1.0344, "pb_flag": false, "source": "5", "date": "12-31", "pb_over_history": 0.4276, "pe_over_history": 0.2116}, {"id": 499147, "index_code": "SP500", "name": "标普500", "ttype": "1", "pe": 29.3914, "pb": 5.5571, "pe_percentile": 0.8908, "pb_percentile": 0.9964, "roe": 0.1891, "yeild": 0.0107, "ts": 1767024000000, "eva_type": "high", "eva_type_int": 2, "url": "https://danjuanfunds.com/funding/096001?channel=1800100001&source=guzhi__web_20171001", "bond_yeild": 0.05, "begin_at": 1441814400000, "created_at": 1767144720110, "updated_at": 1767144720110, "peg": 1.9326, "pb_flag": false, "source": "5", "date": "12-30", "pb_over_history": 0.0036, "pe_over_history": 0.1092}, {"id": 499192, "index_code": "SZ399001", "name": "深证成指", "ttype": "1", "pe": 31.241, "pb": 2.7483, "pe_percentile": 0.8452, "pb_percentile": 0.5072, "roe": 0.088, "yeild": 0.0158, "ts": 1767110400000, "eva_type": "high", "eva_type_int": 2, "url": "https://danjuanfunds.com/funding/163109?channel=1800100001&source=guzhi__web_20171001", "bond_yeild": 0.05, "begin_at": 1442851200000, "created_at": 1767177122785, "updated_at": 1767177122785, "peg": 0.9904, "pb_flag": false, "source": "5", "date": "12-31", "pb_over_history": 0.4928, "pe_over_history": 0.1548}, {"id": 499194, "index_code": "SZ399417", "name": "新能源车", "ttype": "3", "pe": 32.8034, "pb": 4.0515, "pe_percentile": 0.5276, "pb_percentile": 0.6472, "roe": 0.1235, "yeild": 0.0116, "ts": 1767110400000, "eva_type": "high", "eva_type_int": 2, "url": "https://danjuanfunds.com/funding/160225?channel=1800100001&source=guzhi__web_20171001", "bond_yeild": 0.05, "begin_at": 1442851200000, "created_at": 1767177122956, "updated_at": 1767177122956, "peg": 0.856, "pb_flag": true, "source": "5", "date": "12-31", "pb_over_history": 0.3528, "pe_over_history": 0.4724}, {"id": 499163, "index_code": "SH000905", "name": "中证500", "ttype": "1", "pe": 33.802, "pb": 2.3243, "pe_percentile": 0.8012, "pb_percentile": 0.7548, "roe": 0.0688, "yeild": 0.0143, "ts": 1767110400000, "eva_type": "high", "eva_type_int": 2, "url": "https://danjuanfunds.com/funding/000478?channel=1800100001&source=guzhi__web_20171001", "bond_yeild": 0.05, "begin_at": 1442851200000, "created_at": 1767177120442, "updated_at": 1767177120442, "peg": 1.144, "pb_flag": false, "source": "5", "date": "12-31", "pb_over_history": 0.2452, "pe_over_history": 0.1988}, {"id": 499149, "index_code": "NDX", "name": "纳指100", "ttype": "1", "pe": 36.1822, "pb": 10.2697, "pe_percentile": 0.8496, "pb_percentile": 0.9948, "roe": 0.2838, "yeild": 0.0048, "ts": 1767024000000, "eva_type": "high", "eva_type_int": 2, "url": "https://danjuanfunds.com/funding/160213?channel=1800100001&source=guzhi__web_20171001", "bond_yeild": 0.05, "begin_at": 1442505600000, "created_at": 1767144720282, "updated_at": 1767144720282, "peg": 1.7957, "pb_flag": false, "source": "5", "date": "12-30", "pb_over_history": 0.0052, "pe_over_history": 0.1504}, {"id": 499170, "index_code": "SH000827", "name": "中证环保", "ttype": "3", "pe": 37.1759, "pb": 2.718, "pe_percentile": 0.852, "pb_percentile": 0.4572, "roe": 0.0731, "yeild": 0.0154, "ts": 1767110400000, "eva_type": "high", "eva_type_int": 2, "url": "https://danjuanfunds.com/funding/001064?channel=1800100001&source=guzhi__web_20171001", "bond_yeild": 0.05, "begin_at": 1442851200000, "created_at": 1767177121009, "updated_at": 1767177121009, "peg": 0.8506, "pb_flag": false, "source": "5", "date": "12-31", "pb_over_history": 0.5428, "pe_over_history": 0.148}, {"id": 499201, "index_code": "SZ399971", "name": "中证传媒", "ttype": "3", "pe": 38.5853, "pb": 2.5499, "pe_percentile": 0.6096, "pb_percentile": 0.4536, "roe": 0.0661, "yeild": 0.0174, "ts": 1767110400000, "eva_type": "high", "eva_type_int": 2, "url": "https://danjuanfunds.com/funding/004752?channel=1800100001&source=guzhi__web_20171001", "bond_yeild": 0.05, "begin_at": 1442851200000, "created_at": 1767177123571, "updated_at": 1767177123571, "peg": 0.8039, "pb_flag": false, "source": "5", "date": "12-31", "pb_over_history": 0.5464, "pe_over_history": 0.3904}, {"id": 499212, "index_code": "935600", "name": "MSCI印度", "ttype": "1", "pe": 39.8815, "pb": 5.3758, "pe_percentile": 0.8968, "pb_percentile": 0.8968, "roe": 0.1348, "yeild": 0.0091, "ts": 1767110400000, "eva_type": "high", "eva_type_int": 2, "url": "https://danjuanfunds.com/funding/164824?channel=1800100001&source=guzhi__web_20171001", "bond_yeild": 0.05, "begin_at": 1470672000000, "created_at": 1767177124321, "updated_at": 1767177124321, "pb_flag": false, "source": "5", "date": "12-31", "pb_over_history": 0.1032, "pe_over_history": 0.1032}, {"id": 499167, "index_code": "SZ399006", "name": "创业板", "ttype": "1", "pe": 40.7742, "pb": 5.489, "pe_percentile": 0.4096, "pb_percentile": 0.6208, "roe": 0.1346, "yeild": 0.0096, "ts": 1767110400000, "eva_type": "high", "eva_type_int": 2, "url": "https://danjuanfunds.com/funding/110026?channel=1800100001&source=guzhi__web_20171001", "bond_yeild": 0.05, "begin_at": 1442851200000, "created_at": 1767177120777, "updated_at": 1767177120777, "peg": 1.1012, "pb_flag": false, "source": "5", "date": "12-31", "pb_over_history": 0.3792, "pe_over_history": 0.5904}, {"id": 499200, "index_code": "SZ399610", "name": "TMT50", "ttype": "3", "pe": 44.1273, "pb": 5.3914, "pe_percentile": 0.7696, "pb_percentile": 0.8976, "roe": 0.1222, "yeild": 0.0081, "ts": 1767110400000, "eva_type": "high", "eva_type_int": 2, "url": "https://danjuanfunds.com/funding/160224?channel=1800100001&source=guzhi__web_20171001", "bond_yeild": 0.05, "begin_at": 1481817600000, "created_at": 1767177123498, "updated_at": 1767177123498, "peg": 0.8909, "pb_flag": false, "source": "5", "date": "12-31", "pb_over_history": 0.1024, "pe_over_history": 0.2304}, {"id": 499166, "index_code": "SH000852", "name": "中证1000", "ttype": "1", "pe": 46.3043, "pb": 2.4705, "pe_percentile": 0.7136, "pb_percentile": 0.5016, "roe": 0.0534, "yeild": 0.0109, "ts": 1767110400000, "eva_type": "high", "eva_type_int": 2, "url": "https://danjuanfunds.com/funding/003646?channel=1800100001&source=guzhi__web_20171001", "bond_yeild": 0.05, "begin_at": 1442851200000, "created_at": 1767177120689, "updated_at": 1767177120689, "peg": 1.1944, "pb_flag": false, "source": "5", "date": "12-31", "pb_over_history": 0.4984, "pe_over_history": 0.2864}, {"id": 499208, "index_code": "CSI931079", "name": "5G通讯", "ttype": "3", "pe": 50.0947, "pb": 6.2796, "pe_percentile": 0.9753, "pb_percentile": 0.9815, "roe": 0.1254, "yeild": 0.0065, "ts": 1767110400000, "eva_type": "high", "eva_type_int": 2, "url": "", "bond_yeild": 0.05, "begin_at": 1556553600000, "created_at": 1767177124098, "updated_at": 1767177124098, "peg": 0.9425, "pb_flag": false, "source": "5", "date": "12-31", "pb_over_history": 0.0185, "pe_over_history": 0.0247}, {"id": 499198, "index_code": "CSI931087", "name": "科技龙头", "ttype": "3", "pe": 52.9365, "pb": 6.169, "pe_percentile": 0.868, "pb_percentile": 0.7559, "roe": 0.1165, "yeild": 0.0061, "ts": 1767110400000, "eva_type": "high", "eva_type_int": 2, "url": "https://danjuanfunds.com/funding/007873?channel=1800100001&source=guzhi__web_20171001", "bond_yeild": 0.05, "begin_at": 1553011200000, "created_at": 1767177123356, "updated_at": 1767177123356, "peg": 1.1059, "pb_flag": false, "source": "5", "date": "12-31", "pb_over_history": 0.2441, "pe_over_history": 0.132}, {"id": 499206, "index_code": "CSI930652", "name": "中证电子", "ttype": "3", "pe": 59.3953, "pb": 5.5575, "pe_percentile": 0.9476, "pb_percentile": 0.9716, "roe": 0.0936, "yeild": 0.0061, "ts": 1767110400000, "eva_type": "high", "eva_type_int": 2, "url": "", "bond_yeild": 0.05, "begin_at": 1442764800000, "created_at": 1767177123937, "updated_at": 1767177123937, "peg": 1.0825, "pb_flag": false, "source": "5", "date": "12-31", "pb_over_history": 0.0284, "pe_over_history": 0.0524}, {"id": 499179, "index_code": "SH000993", "name": "全指信息", "ttype": "3", "pe": 67.5781, "pb": 5.5357, "pe_percentile": 0.802, "pb_percentile": 0.9288, "roe": 0.0819, "yeild": 0.0058, "ts": 1767110400000, "eva_type": "high", "eva_type_int": 2, "url": "https://danjuanfunds.com/funding/002974?channel=1800100001&source=guzhi__web_20171001", "bond_yeild": 0.05, "begin_at": 1442851200000, "created_at": 1767177121742, "updated_at": 1767177121742, "peg": 1.0978, "pb_flag": false, "source": "5", "date": "12-31", "pb_over_history": 0.0712, "pe_over_history": 0.198}, {"id": 499173, "index_code": "SZ399967", "name": "中证军工", "ttype": "3", "pe": 115.4787, "pb": 3.9794, "pe_percentile": 0.844, "pb_percentile": 0.8312, "roe": 0.0345, "yeild": 0.0042, "ts": 1767110400000, "eva_type": "high", "eva_type_int": 2, "url": "https://danjuanfunds.com/funding/163115?channel=1800100001&source=guzhi__web_20171001", "bond_yeild": 0.05, "begin_at": 1442851200000, "created_at": 1767177121288, "updated_at": 1767177121288, "peg": 1.3444, "pb_flag": true, "source": "5", "date": "12-31", "pb_over_history": 0.1688, "pe_over_history": 0.156}, {"id": 499209, "index_code": "SH000688", "name": "科创50", "ttype": "1", "pe": 161.142, "pb": 6.1421, "pe_percentile": 0.965, "pb_percentile": 0.6623, "roe": 0.0381, "yeild": 0.0036, "ts": 1767110400000, "eva_type": "high", "eva_type_int": 2, "url": "", "bond_yeild": 0.05, "begin_at": 1577721600000, "created_at": 1767177124150, "updated_at": 1767177124150, "peg": 2.1947, "pb_flag": false, "source": "5", "date": "12-31", "pb_over_history": 0.3377, "pe_over_history": 0.035}], "current_page": 1, "size": 63, "total_items": 63, "total_pages": 1}, "result_code": 0}